herald/__init__.py
herald/admin.py
herald/apps.py
herald/base.py
herald/models.py
herald/urls.py
herald/views.py
herald/contrib/__init__.py
herald/contrib/auth/__init__.py
herald/contrib/auth/apps.py
herald/contrib/auth/forms.py
herald/contrib/auth/notifications.py
herald/contrib/auth/templates/herald/html/password_reset.html
herald/contrib/auth/templates/herald/text/password_reset.txt
herald/management/__init__.py
herald/management/commands/__init__.py
herald/management/commands/delnotifs.py
herald/migrations/0001_initial.py
herald/migrations/0002_sentnotification_attachments.py
herald/migrations/0003_auto_20170830_1617.py
herald/migrations/0004_auto_20171009_0906.py
herald/migrations/0005_auto_20180516_1755.py
herald/migrations/__init__.py
herald/templates/herald/test/notification_list.html
django_herald-0.3.0.dist-info/LICENSE
django_herald-0.3.0.dist-info/METADATA
django_herald-0.3.0.dist-info/WHEEL
django_herald-0.3.0.dist-info/top_level.txt
django_herald-0.3.0.dist-info/RECORD
