Metadata-Version: 2.1
Name: django-herald
Version: 0.3.0
Summary: Django library for separating the message content from transmission method
Home-page: https://github.com/worthwhile/django-herald/
Author: Worthwhile
Author-email: devs@worthwhile.com
License: MIT
Download-URL: https://github.com/worthwhile/django-herald/tarball/0.3.0
Keywords: django,notifications,messaging
Platform: UNKNOWN
Classifier: Framework :: Django
Classifier: Intended Audience :: Developers
Classifier: Programming Language :: Python
Classifier: Programming Language :: Python :: 3
Classifier: Programming Language :: Python :: 3.7
Classifier: Programming Language :: Python :: 3.8
Classifier: Programming Language :: Python :: 3.9
Classifier: Programming Language :: Python :: 3.10
Classifier: Programming Language :: Python :: 3 :: Only
Classifier: License :: OSI Approved :: MIT License
License-File: LICENSE
Requires-Dist: django (>=3.2)
Requires-Dist: six
Requires-Dist: jsonpickle
Provides-Extra: dev
Requires-Dist: django (>=3.2) ; extra == 'dev'
Requires-Dist: six ; extra == 'dev'
Requires-Dist: jsonpickle ; extra == 'dev'
Requires-Dist: pytz ; extra == 'dev'
Provides-Extra: html2text
Requires-Dist: html2text ; extra == 'html2text'
Provides-Extra: twilio
Requires-Dist: twilio ; extra == 'twilio'
